odoo/addons/sale_purchase_stock_line_note/README.rst
odoo/addons/sale_purchase_stock_line_note/__init__.py
odoo/addons/sale_purchase_stock_line_note/__manifest__.py
odoo/addons/sale_purchase_stock_line_note/i18n/it.po
odoo/addons/sale_purchase_stock_line_note/i18n/sale_purchase_stock_line_note.pot
odoo/addons/sale_purchase_stock_line_note/models/__init__.py
odoo/addons/sale_purchase_stock_line_note/models/purchase_order_line.py
odoo/addons/sale_purchase_stock_line_note/models/res_config_settings.py
odoo/addons/sale_purchase_stock_line_note/models/sale_order_line.py
odoo/addons/sale_purchase_stock_line_note/models/stock_move.py
odoo/addons/sale_purchase_stock_line_note/models/stock_move_line.py
odoo/addons/sale_purchase_stock_line_note/models/stock_rule.py
odoo/addons/sale_purchase_stock_line_note/readme/CONFIGURE.md
odoo/addons/sale_purchase_stock_line_note/readme/CONTRIBUTORS.md
odoo/addons/sale_purchase_stock_line_note/readme/DESCRIPTION.md
odoo/addons/sale_purchase_stock_line_note/report/report_stockpicking_operations.xml
odoo/addons/sale_purchase_stock_line_note/security/security.xml
odoo/addons/sale_purchase_stock_line_note/static/description/icon.png
odoo/addons/sale_purchase_stock_line_note/static/description/index.html
odoo/addons/sale_purchase_stock_line_note/tests/__init__.py
odoo/addons/sale_purchase_stock_line_note/tests/test_sale_stock_purchase_line_note.py
odoo/addons/sale_purchase_stock_line_note/views/purchase_order.xml
odoo/addons/sale_purchase_stock_line_note/views/res_config_settings_views.xml
odoo/addons/sale_purchase_stock_line_note/views/stock_move_line_views.xml
odoo/addons/sale_purchase_stock_line_note/views/stock_picking.xml
odoo14_addon_sale_purchase_stock_line_note-14.0.1.1.0.dist-info/METADATA
odoo14_addon_sale_purchase_stock_line_note-14.0.1.1.0.dist-info/WHEEL
odoo14_addon_sale_purchase_stock_line_note-14.0.1.1.0.dist-info/top_level.txt
odoo14_addon_sale_purchase_stock_line_note-14.0.1.1.0.dist-info/RECORD
