Metadata-Version: 2.1
Name: odoo14-addon-sale-purchase-stock-line-note
Version: 14.0.1.1.0
Summary: Propagate sale line note to stock move and purchase
Home-page: https://github.com/OCA/stock-logistics-workflow
Author: Camptocamp, Odoo Community Association (OCA)
Author-email: support@odoo-community.org
License: AGPL-3
Platform: UNKNOWN
Classifier: Programming Language :: Python
Classifier: Framework :: Odoo
Classifier: Framework :: Odoo :: 14.0
Classifier: License :: OSI Approved :: GNU Affero General Public License v3
Classifier: Development Status :: 4 - Beta
Requires-Python: >=3.6
Requires-Dist: odoo14-addon-sale-order-line-note
Requires-Dist: odoo <14.1dev,>=14.0a
